[
    {
        "id": 31883249,
        "date": "2022-07-29",
        "billable": false,
        "minutes": 480,
        "description": "",
        "created_at": "2022-07-29T09:16:07Z",
        "updated_at": "2022-07-29T09:16:23Z",
        "approved_at": null,
        "source_url": null,
        "user": {
            "id": 78165,
            "email": "some.person@armakuni.com",
            "first_name": "Some",
            "last_name": "Person",
            "profile_image_url": "https://cdn.nokotime.com/images/user_icons/default-ig-72x722x.png",
            "url": "https://api.nokotime.com/v2/users/12345"
        },
        "approved_by": null,
        "tags": [],
        "project": {
            "id": 603670,
            "name": "Some project",
            "billing_increment": 5,
            "enabled": true,
            "billable": false,
            "color": "#ef63a2",
            "url": "https://api.nokotime.com/v2/projects/123456"
        },
        "url": "https://api.nokotime.com/v2/entries/31883249",
        "invoiced_outside_of_freckle_url": "https://api.nokotime.com/v2/entries/31883249/invoiced_outside_of_freckle",
        "invoiced_outside_of_noko_url": "https://api.nokotime.com/v2/entries/31883249/marked_as_invoiced",
        "approved_url": "https://api.nokotime.com/v2/entries/31883249/approved",
        "unapproved_url": "https://api.nokotime.com/v2/entries/31883249/unapproved"
    },
    {
        "id": 31883252,
        "date": "2022-07-28",
        "billable": false,
        "minutes": 360,
        "description": "",
        "created_at": "2022-07-29T09:17:11Z",
        "updated_at": "2022-07-29T09:17:11Z",
        "approved_at": null,
        "source_url": null,
        "user": {
            "id": 78165,
            "email": "some.person@armakuni.com",
            "first_name": "Some",
            "last_name": "Person",
            "profile_image_url": "https://cdn.nokotime.com/images/user_icons/default-ig-72x722x.png",
            "url": "https://api.nokotime.com/v2/users/12345"
        },
        "approved_by": null,
        "tags": [],
        "project": {
            "id": 609863,
            "name": "Some project",
            "billing_increment": 5,
            "enabled": true,
            "billable": false,
            "color": "#ef5555",
            "url": "https://api.nokotime.com/v2/projects/123456"
        },
        "url": "https://api.nokotime.com/v2/entries/31883252",
        "invoiced_outside_of_freckle_url": "https://api.nokotime.com/v2/entries/31883252/invoiced_outside_of_freckle",
        "invoiced_outside_of_noko_url": "https://api.nokotime.com/v2/entries/31883252/marked_as_invoiced",
        "approved_url": "https://api.nokotime.com/v2/entries/31883252/approved",
        "unapproved_url": "https://api.nokotime.com/v2/entries/31883252/unapproved"
    },
    {
        "id": 31883247,
        "date": "2022-07-28",
        "billable": true,
        "minutes": 120,
        "description": "",
        "created_at": "2022-07-29T09:15:32Z",
        "updated_at": "2022-07-29T09:15:32Z",
        "approved_at": null,
        "source_url": null,
        "user": {
            "id": 78165,
            "email": "some.person@armakuni.com",
            "first_name": "Some",
            "last_name": "Person",
            "profile_image_url": "https://cdn.nokotime.com/images/user_icons/default-ig-72x722x.png",
            "url": "https://api.nokotime.com/v2/users/12345"
        },
        "approved_by": null,
        "tags": [],
        "project": {
            "id": 658433,
            "name": "Some project",
            "billing_increment": 60,
            "enabled": true,
            "billable": true,
            "color": "#86ac2a",
            "url": "https://api.nokotime.com/v2/projects/123456"
        },
        "url": "https://api.nokotime.com/v2/entries/31883247",
        "invoiced_outside_of_freckle_url": "https://api.nokotime.com/v2/entries/31883247/invoiced_outside_of_freckle",
        "invoiced_outside_of_noko_url": "https://api.nokotime.com/v2/entries/31883247/marked_as_invoiced",
        "approved_url": "https://api.nokotime.com/v2/entries/31883247/approved",
        "unapproved_url": "https://api.nokotime.com/v2/entries/31883247/unapproved"
    },
    {
        "id": 31883251,
        "date": "2022-07-27",
        "billable": false,
        "minutes": 240,
        "description": "",
        "created_at": "2022-07-29T09:17:02Z",
        "updated_at": "2022-07-29T09:17:02Z",
        "approved_at": null,
        "source_url": null,
        "user": {
            "id": 78165,
            "email": "some.person@armakuni.com",
            "first_name": "Some",
            "last_name": "Person",
            "profile_image_url": "https://cdn.nokotime.com/images/user_icons/default-ig-72x722x.png",
            "url": "https://api.nokotime.com/v2/users/12345"
        },
        "approved_by": null,
        "tags": [],
        "project": {
            "id": 609863,
            "name": "Some project",
            "billing_increment": 5,
            "enabled": true,
            "billable": false,
            "color": "#ef5555",
            "url": "https://api.nokotime.com/v2/projects/123456"
        },
        "url": "https://api.nokotime.com/v2/entries/31883251",
        "invoiced_outside_of_freckle_url": "https://api.nokotime.com/v2/entries/31883251/invoiced_outside_of_freckle",
        "invoiced_outside_of_noko_url": "https://api.nokotime.com/v2/entries/31883251/marked_as_invoiced",
        "approved_url": "https://api.nokotime.com/v2/entries/31883251/approved",
        "unapproved_url": "https://api.nokotime.com/v2/entries/31883251/unapproved"
    },
    {
        "id": 31883245,
        "date": "2022-07-27",
        "billable": true,
        "minutes": 240,
        "description": "",
        "created_at": "2022-07-29T09:14:53Z",
        "updated_at": "2022-07-29T09:14:53Z",
        "approved_at": null,
        "source_url": null,
        "user": {
            "id": 78165,
            "email": "some.person@armakuni.com",
            "first_name": "Some",
            "last_name": "Person",
            "profile_image_url": "https://cdn.nokotime.com/images/user_icons/default-ig-72x722x.png",
            "url": "https://api.nokotime.com/v2/users/12345"
        },
        "approved_by": null,
        "tags": [],
        "project": {
            "id": 658433,
            "name": "Some project",
            "billing_increment": 60,
            "enabled": true,
            "billable": true,
            "color": "#86ac2a",
            "url": "https://api.nokotime.com/v2/projects/123456"
        },
        "url": "https://api.nokotime.com/v2/entries/31883245",
        "invoiced_outside_of_freckle_url": "https://api.nokotime.com/v2/entries/31883245/invoiced_outside_of_freckle",
        "invoiced_outside_of_noko_url": "https://api.nokotime.com/v2/entries/31883245/marked_as_invoiced",
        "approved_url": "https://api.nokotime.com/v2/entries/31883245/approved",
        "unapproved_url": "https://api.nokotime.com/v2/entries/31883245/unapproved"
    },
    {
        "id": 31883250,
        "date": "2022-07-26",
        "billable": false,
        "minutes": 180,
        "description": "",
        "created_at": "2022-07-29T09:16:52Z",
        "updated_at": "2022-07-29T09:16:52Z",
        "approved_at": null,
        "source_url": null,
        "user": {
            "id": 78165,
            "email": "some.person@armakuni.com",
            "first_name": "Some",
            "last_name": "Person",
            "profile_image_url": "https://cdn.nokotime.com/images/user_icons/default-ig-72x722x.png",
            "url": "https://api.nokotime.com/v2/users/12345"
        },
        "approved_by": null,
        "tags": [],
        "project": {
            "id": 609863,
            "name": "Some project",
            "billing_increment": 5,
            "enabled": true,
            "billable": false,
            "color": "#ef5555",
            "url": "https://api.nokotime.com/v2/projects/123456"
        },
        "url": "https://api.nokotime.com/v2/entries/31883250",
        "invoiced_outside_of_freckle_url": "https://api.nokotime.com/v2/entries/31883250/invoiced_outside_of_freckle",
        "invoiced_outside_of_noko_url": "https://api.nokotime.com/v2/entries/31883250/marked_as_invoiced",
        "approved_url": "https://api.nokotime.com/v2/entries/31883250/approved",
        "unapproved_url": "https://api.nokotime.com/v2/entries/31883250/unapproved"
    },
    {
        "id": 31883242,
        "date": "2022-07-26",
        "billable": true,
        "minutes": 60,
        "description": "",
        "created_at": "2022-07-29T09:14:29Z",
        "updated_at": "2022-07-29T09:14:29Z",
        "approved_at": null,
        "source_url": null,
        "user": {
            "id": 78165,
            "email": "some.person@armakuni.com",
            "first_name": "Some",
            "last_name": "Person",
            "profile_image_url": "https://cdn.nokotime.com/images/user_icons/default-ig-72x722x.png",
            "url": "https://api.nokotime.com/v2/users/12345"
        },
        "approved_by": null,
        "tags": [],
        "project": {
            "id": 654894,
            "name": "Some project",
            "billing_increment": 60,
            "enabled": true,
            "billable": true,
            "color": "#0f6953",
            "url": "https://api.nokotime.com/v2/projects/123456"
        },
        "url": "https://api.nokotime.com/v2/entries/31883242",
        "invoiced_outside_of_freckle_url": "https://api.nokotime.com/v2/entries/31883242/invoiced_outside_of_freckle",
        "invoiced_outside_of_noko_url": "https://api.nokotime.com/v2/entries/31883242/marked_as_invoiced",
        "approved_url": "https://api.nokotime.com/v2/entries/31883242/approved",
        "unapproved_url": "https://api.nokotime.com/v2/entries/31883242/unapproved"
    },
    {
        "id": 31883241,
        "date": "2022-07-26",
        "billable": true,
        "minutes": 240,
        "description": "",
        "created_at": "2022-07-29T09:14:15Z",
        "updated_at": "2022-07-29T09:14:15Z",
        "approved_at": null,
        "source_url": null,
        "user": {
            "id": 78165,
            "email": "some.person@armakuni.com",
            "first_name": "Some",
            "last_name": "Person",
            "profile_image_url": "https://cdn.nokotime.com/images/user_icons/default-ig-72x722x.png",
            "url": "https://api.nokotime.com/v2/users/12345"
        },
        "approved_by": null,
        "tags": [],
        "project": {
            "id": 658433,
            "name": "Some project",
            "billing_increment": 60,
            "enabled": true,
            "billable": true,
            "color": "#86ac2a",
            "url": "https://api.nokotime.com/v2/projects/123456"
        },
        "url": "https://api.nokotime.com/v2/entries/31883241",
        "invoiced_outside_of_freckle_url": "https://api.nokotime.com/v2/entries/31883241/invoiced_outside_of_freckle",
        "invoiced_outside_of_noko_url": "https://api.nokotime.com/v2/entries/31883241/marked_as_invoiced",
        "approved_url": "https://api.nokotime.com/v2/entries/31883241/approved",
        "unapproved_url": "https://api.nokotime.com/v2/entries/31883241/unapproved"
    },
    {
        "id": 31883239,
        "date": "2022-07-25",
        "billable": true,
        "minutes": 240,
        "description": "",
        "created_at": "2022-07-29T09:13:29Z",
        "updated_at": "2022-07-29T09:13:29Z",
        "approved_at": null,
        "source_url": null,
        "user": {
            "id": 78165,
            "email": "some.person@armakuni.com",
            "first_name": "Some",
            "last_name": "Person",
            "profile_image_url": "https://cdn.nokotime.com/images/user_icons/default-ig-72x722x.png",
            "url": "https://api.nokotime.com/v2/users/12345"
        },
        "approved_by": null,
        "tags": [],
        "project": {
            "id": 658433,
            "name": "Some project",
            "billing_increment": 60,
            "enabled": true,
            "billable": true,
            "color": "#86ac2a",
            "url": "https://api.nokotime.com/v2/projects/123456"
        },
        "url": "https://api.nokotime.com/v2/entries/31883239",
        "invoiced_outside_of_freckle_url": "https://api.nokotime.com/v2/entries/31883239/invoiced_outside_of_freckle",
        "invoiced_outside_of_noko_url": "https://api.nokotime.com/v2/entries/31883239/marked_as_invoiced",
        "approved_url": "https://api.nokotime.com/v2/entries/31883239/approved",
        "unapproved_url": "https://api.nokotime.com/v2/entries/31883239/unapproved"
    },
    {
        "id": 31883014,
        "date": "2022-07-25",
        "billable": true,
        "minutes": 240,
        "description": "",
        "created_at": "2022-07-29T08:30:19Z",
        "updated_at": "2022-07-29T08:30:19Z",
        "approved_at": null,
        "source_url": null,
        "user": {
            "id": 78165,
            "email": "some.person@armakuni.com",
            "first_name": "Some",
            "last_name": "Person",
            "profile_image_url": "https://cdn.nokotime.com/images/user_icons/default-ig-72x722x.png",
            "url": "https://api.nokotime.com/v2/users/12345"
        },
        "approved_by": null,
        "tags": [],
        "project": {
            "id": 654894,
            "name": "Some project",
            "billing_increment": 60,
            "enabled": true,
            "billable": true,
            "color": "#0f6953",
            "url": "https://api.nokotime.com/v2/projects/123456"
        },
        "url": "https://api.nokotime.com/v2/entries/31883014",
        "invoiced_outside_of_freckle_url": "https://api.nokotime.com/v2/entries/31883014/invoiced_outside_of_freckle",
        "invoiced_outside_of_noko_url": "https://api.nokotime.com/v2/entries/31883014/marked_as_invoiced",
        "approved_url": "https://api.nokotime.com/v2/entries/31883014/approved",
        "unapproved_url": "https://api.nokotime.com/v2/entries/31883014/unapproved"
    },
    {
        "id": 31845794,
        "date": "2022-07-22",
        "billable": false,
        "minutes": 420,
        "description": "",
        "created_at": "2022-07-24T12:34:37Z",
        "updated_at": "2022-07-24T12:34:37Z",
        "approved_at": null,
        "source_url": null,
        "user": {
            "id": 78165,
            "email": "some.person@armakuni.com",
            "first_name": "Some",
            "last_name": "Person",
            "profile_image_url": "https://cdn.nokotime.com/images/user_icons/default-ig-72x722x.png",
            "url": "https://api.nokotime.com/v2/users/12345"
        },
        "approved_by": null,
        "tags": [],
        "project": {
            "id": 609863,
            "name": "Some project",
            "billing_increment": 5,
            "enabled": true,
            "billable": false,
            "color": "#ef5555",
            "url": "https://api.nokotime.com/v2/projects/123456"
        },
        "url": "https://api.nokotime.com/v2/entries/31845794",
        "invoiced_outside_of_freckle_url": "https://api.nokotime.com/v2/entries/31845794/invoiced_outside_of_freckle",
        "invoiced_outside_of_noko_url": "https://api.nokotime.com/v2/entries/31845794/marked_as_invoiced",
        "approved_url": "https://api.nokotime.com/v2/entries/31845794/approved",
        "unapproved_url": "https://api.nokotime.com/v2/entries/31845794/unapproved"
    },
    {
        "id": 31845793,
        "date": "2022-07-22",
        "billable": false,
        "minutes": 60,
        "description": "Strategy playback",
        "created_at": "2022-07-24T12:34:21Z",
        "updated_at": "2022-07-24T12:34:21Z",
        "approved_at": null,
        "source_url": null,
        "user": {
            "id": 78165,
            "email": "some.person@armakuni.com",
            "first_name": "Some",
            "last_name": "Person",
            "profile_image_url": "https://cdn.nokotime.com/images/user_icons/default-ig-72x722x.png",
            "url": "https://api.nokotime.com/v2/users/12345"
        },
        "approved_by": null,
        "tags": [],
        "project": {
            "id": 620570,
            "name": "Some project",
            "billing_increment": 5,
            "enabled": true,
            "billable": false,
            "color": "#0f6953",
            "url": "https://api.nokotime.com/v2/projects/123456"
        },
        "url": "https://api.nokotime.com/v2/entries/31845793",
        "invoiced_outside_of_freckle_url": "https://api.nokotime.com/v2/entries/31845793/invoiced_outside_of_freckle",
        "invoiced_outside_of_noko_url": "https://api.nokotime.com/v2/entries/31845793/marked_as_invoiced",
        "approved_url": "https://api.nokotime.com/v2/entries/31845793/approved",
        "unapproved_url": "https://api.nokotime.com/v2/entries/31845793/unapproved"
    },
    {
        "id": 31845792,
        "date": "2022-07-21",
        "billable": false,
        "minutes": 480,
        "description": "",
        "created_at": "2022-07-24T12:33:25Z",
        "updated_at": "2022-07-24T12:33:25Z",
        "approved_at": null,
        "source_url": null,
        "user": {
            "id": 78165,
            "email": "some.person@armakuni.com",
            "first_name": "Some",
            "last_name": "Person",
            "profile_image_url": "https://cdn.nokotime.com/images/user_icons/default-ig-72x722x.png",
            "url": "https://api.nokotime.com/v2/users/12345"
        },
        "approved_by": null,
        "tags": [],
        "project": {
            "id": 609863,
            "name": "Some project",
            "billing_increment": 5,
            "enabled": true,
            "billable": false,
            "color": "#ef5555",
            "url": "https://api.nokotime.com/v2/projects/123456"
        },
        "url": "https://api.nokotime.com/v2/entries/31845792",
        "invoiced_outside_of_freckle_url": "https://api.nokotime.com/v2/entries/31845792/invoiced_outside_of_freckle",
        "invoiced_outside_of_noko_url": "https://api.nokotime.com/v2/entries/31845792/marked_as_invoiced",
        "approved_url": "https://api.nokotime.com/v2/entries/31845792/approved",
        "unapproved_url": "https://api.nokotime.com/v2/entries/31845792/unapproved"
    },
    {
        "id": 31849225,
        "date": "2022-07-20",
        "billable": true,
        "minutes": 60,
        "description": "",
        "created_at": "2022-07-25T08:14:01Z",
        "updated_at": "2022-07-25T08:14:01Z",
        "approved_at": null,
        "source_url": null,
        "user": {
            "id": 78165,
            "email": "some.person@armakuni.com",
            "first_name": "Some",
            "last_name": "Person",
            "profile_image_url": "https://cdn.nokotime.com/images/user_icons/default-ig-72x722x.png",
            "url": "https://api.nokotime.com/v2/users/12345"
        },
        "approved_by": null,
        "tags": [],
        "project": {
            "id": 658720,
            "name": "Some project",
            "billing_increment": 60,
            "enabled": true,
            "billable": true,
            "color": "#13a480",
            "url": "https://api.nokotime.com/v2/projects/123456"
        },
        "url": "https://api.nokotime.com/v2/entries/31849225",
        "invoiced_outside_of_freckle_url": "https://api.nokotime.com/v2/entries/31849225/invoiced_outside_of_freckle",
        "invoiced_outside_of_noko_url": "https://api.nokotime.com/v2/entries/31849225/marked_as_invoiced",
        "approved_url": "https://api.nokotime.com/v2/entries/31849225/approved",
        "unapproved_url": "https://api.nokotime.com/v2/entries/31849225/unapproved"
    },
    {
        "id": 31845791,
        "date": "2022-07-20",
        "billable": false,
        "minutes": 180,
        "description": "",
        "created_at": "2022-07-24T12:32:56Z",
        "updated_at": "2022-07-24T12:32:56Z",
        "approved_at": null,
        "source_url": null,
        "user": {
            "id": 78165,
            "email": "some.person@armakuni.com",
            "first_name": "Some",
            "last_name": "Person",
            "profile_image_url": "https://cdn.nokotime.com/images/user_icons/default-ig-72x722x.png",
            "url": "https://api.nokotime.com/v2/users/12345"
        },
        "approved_by": null,
        "tags": [],
        "project": {
            "id": 609863,
            "name": "Some project",
            "billing_increment": 5,
            "enabled": true,
            "billable": false,
            "color": "#ef5555",
            "url": "https://api.nokotime.com/v2/projects/123456"
        },
        "url": "https://api.nokotime.com/v2/entries/31845791",
        "invoiced_outside_of_freckle_url": "https://api.nokotime.com/v2/entries/31845791/invoiced_outside_of_freckle",
        "invoiced_outside_of_noko_url": "https://api.nokotime.com/v2/entries/31845791/marked_as_invoiced",
        "approved_url": "https://api.nokotime.com/v2/entries/31845791/approved",
        "unapproved_url": "https://api.nokotime.com/v2/entries/31845791/unapproved"
    },
    {
        "id": 31845786,
        "date": "2022-07-20",
        "billable": true,
        "minutes": 240,
        "description": "",
        "created_at": "2022-07-24T12:30:10Z",
        "updated_at": "2022-07-24T12:30:10Z",
        "approved_at": null,
        "source_url": null,
        "user": {
            "id": 78165,
            "email": "some.person@armakuni.com",
            "first_name": "Some",
            "last_name": "Person",
            "profile_image_url": "https://cdn.nokotime.com/images/user_icons/default-ig-72x722x.png",
            "url": "https://api.nokotime.com/v2/users/12345"
        },
        "approved_by": null,
        "tags": [],
        "project": {
            "id": 654894,
            "name": "Some project",
            "billing_increment": 60,
            "enabled": true,
            "billable": true,
            "color": "#0f6953",
            "url": "https://api.nokotime.com/v2/projects/123456"
        },
        "url": "https://api.nokotime.com/v2/entries/31845786",
        "invoiced_outside_of_freckle_url": "https://api.nokotime.com/v2/entries/31845786/invoiced_outside_of_freckle",
        "invoiced_outside_of_noko_url": "https://api.nokotime.com/v2/entries/31845786/marked_as_invoiced",
        "approved_url": "https://api.nokotime.com/v2/entries/31845786/approved",
        "unapproved_url": "https://api.nokotime.com/v2/entries/31845786/unapproved"
    },
    {
        "id": 31845785,
        "date": "2022-07-19",
        "billable": false,
        "minutes": 360,
        "description": "",
        "created_at": "2022-07-24T12:29:39Z",
        "updated_at": "2022-07-24T12:29:39Z",
        "approved_at": null,
        "source_url": null,
        "user": {
            "id": 78165,
            "email": "some.person@armakuni.com",
            "first_name": "Some",
            "last_name": "Person",
            "profile_image_url": "https://cdn.nokotime.com/images/user_icons/default-ig-72x722x.png",
            "url": "https://api.nokotime.com/v2/users/12345"
        },
        "approved_by": null,
        "tags": [],
        "project": {
            "id": 609863,
            "name": "Some project",
            "billing_increment": 5,
            "enabled": true,
            "billable": false,
            "color": "#ef5555",
            "url": "https://api.nokotime.com/v2/projects/123456"
        },
        "url": "https://api.nokotime.com/v2/entries/31845785",
        "invoiced_outside_of_freckle_url": "https://api.nokotime.com/v2/entries/31845785/invoiced_outside_of_freckle",
        "invoiced_outside_of_noko_url": "https://api.nokotime.com/v2/entries/31845785/marked_as_invoiced",
        "approved_url": "https://api.nokotime.com/v2/entries/31845785/approved",
        "unapproved_url": "https://api.nokotime.com/v2/entries/31845785/unapproved"
    },
    {
        "id": 31845784,
        "date": "2022-07-19",
        "billable": true,
        "minutes": 120,
        "description": "",
        "created_at": "2022-07-24T12:29:25Z",
        "updated_at": "2022-07-24T12:29:46Z",
        "approved_at": null,
        "source_url": null,
        "user": {
            "id": 78165,
            "email": "some.person@armakuni.com",
            "first_name": "Some",
            "last_name": "Person",
            "profile_image_url": "https://cdn.nokotime.com/images/user_icons/default-ig-72x722x.png",
            "url": "https://api.nokotime.com/v2/users/12345"
        },
        "approved_by": null,
        "tags": [],
        "project": {
            "id": 654894,
            "name": "Some project",
            "billing_increment": 60,
            "enabled": true,
            "billable": true,
            "color": "#0f6953",
            "url": "https://api.nokotime.com/v2/projects/123456"
        },
        "url": "https://api.nokotime.com/v2/entries/31845784",
        "invoiced_outside_of_freckle_url": "https://api.nokotime.com/v2/entries/31845784/invoiced_outside_of_freckle",
        "invoiced_outside_of_noko_url": "https://api.nokotime.com/v2/entries/31845784/marked_as_invoiced",
        "approved_url": "https://api.nokotime.com/v2/entries/31845784/approved",
        "unapproved_url": "https://api.nokotime.com/v2/entries/31845784/unapproved"
    },
    {
        "id": 31845783,
        "date": "2022-07-18",
        "billable": true,
        "minutes": 360,
        "description": "",
        "created_at": "2022-07-24T12:28:47Z",
        "updated_at": "2022-07-24T12:28:47Z",
        "approved_at": null,
        "source_url": null,
        "user": {
            "id": 78165,
            "email": "some.person@armakuni.com",
            "first_name": "Some",
            "last_name": "Person",
            "profile_image_url": "https://cdn.nokotime.com/images/user_icons/default-ig-72x722x.png",
            "url": "https://api.nokotime.com/v2/users/12345"
        },
        "approved_by": null,
        "tags": [],
        "project": {
            "id": 654894,
            "name": "Some project",
            "billing_increment": 60,
            "enabled": true,
            "billable": true,
            "color": "#0f6953",
            "url": "https://api.nokotime.com/v2/projects/123456"
        },
        "url": "https://api.nokotime.com/v2/entries/31845783",
        "invoiced_outside_of_freckle_url": "https://api.nokotime.com/v2/entries/31845783/invoiced_outside_of_freckle",
        "invoiced_outside_of_noko_url": "https://api.nokotime.com/v2/entries/31845783/marked_as_invoiced",
        "approved_url": "https://api.nokotime.com/v2/entries/31845783/approved",
        "unapproved_url": "https://api.nokotime.com/v2/entries/31845783/unapproved"
    },
    {
        "id": 31845782,
        "date": "2022-07-18",
        "billable": false,
        "minutes": 120,
        "description": "",
        "created_at": "2022-07-24T12:28:35Z",
        "updated_at": "2022-07-24T12:28:35Z",
        "approved_at": null,
        "source_url": null,
        "user": {
            "id": 78165,
            "email": "some.person@armakuni.com",
            "first_name": "Some",
            "last_name": "Person",
            "profile_image_url": "https://cdn.nokotime.com/images/user_icons/default-ig-72x722x.png",
            "url": "https://api.nokotime.com/v2/users/12345"
        },
        "approved_by": null,
        "tags": [],
        "project": {
            "id": 609863,
            "name": "Some project",
            "billing_increment": 5,
            "enabled": true,
            "billable": false,
            "color": "#ef5555",
            "url": "https://api.nokotime.com/v2/projects/123456"
        },
        "url": "https://api.nokotime.com/v2/entries/31845782",
        "invoiced_outside_of_freckle_url": "https://api.nokotime.com/v2/entries/31845782/invoiced_outside_of_freckle",
        "invoiced_outside_of_noko_url": "https://api.nokotime.com/v2/entries/31845782/marked_as_invoiced",
        "approved_url": "https://api.nokotime.com/v2/entries/31845782/approved",
        "unapproved_url": "https://api.nokotime.com/v2/entries/31845782/unapproved"
    },
    {
        "id": 31803932,
        "date": "2022-07-15",
        "billable": false,
        "minutes": 420,
        "description": "",
        "created_at": "2022-07-18T07:57:33Z",
        "updated_at": "2022-07-18T07:57:33Z",
        "approved_at": null,
        "source_url": null,
        "user": {
            "id": 78165,
            "email": "some.person@armakuni.com",
            "first_name": "Some",
            "last_name": "Person",
            "profile_image_url": "https://cdn.nokotime.com/images/user_icons/default-ig-72x722x.png",
            "url": "https://api.nokotime.com/v2/users/12345"
        },
        "approved_by": null,
        "tags": [],
        "project": {
            "id": 609863,
            "name": "Some project",
            "billing_increment": 5,
            "enabled": true,
            "billable": false,
            "color": "#ef5555",
            "url": "https://api.nokotime.com/v2/projects/123456"
        },
        "url": "https://api.nokotime.com/v2/entries/31803932",
        "invoiced_outside_of_freckle_url": "https://api.nokotime.com/v2/entries/31803932/invoiced_outside_of_freckle",
        "invoiced_outside_of_noko_url": "https://api.nokotime.com/v2/entries/31803932/marked_as_invoiced",
        "approved_url": "https://api.nokotime.com/v2/entries/31803932/approved",
        "unapproved_url": "https://api.nokotime.com/v2/entries/31803932/unapproved"
    },
    {
        "id": 31803930,
        "date": "2022-07-15",
        "billable": true,
        "minutes": 60,
        "description": "",
        "created_at": "2022-07-18T07:57:18Z",
        "updated_at": "2022-07-18T07:57:18Z",
        "approved_at": null,
        "source_url": null,
        "user": {
            "id": 78165,
            "email": "some.person@armakuni.com",
            "first_name": "Some",
            "last_name": "Person",
            "profile_image_url": "https://cdn.nokotime.com/images/user_icons/default-ig-72x722x.png",
            "url": "https://api.nokotime.com/v2/users/12345"
        },
        "approved_by": null,
        "tags": [],
        "project": {
            "id": 654894,
            "name": "Some project",
            "billing_increment": 60,
            "enabled": true,
            "billable": true,
            "color": "#0f6953",
            "url": "https://api.nokotime.com/v2/projects/123456"
        },
        "url": "https://api.nokotime.com/v2/entries/31803930",
        "invoiced_outside_of_freckle_url": "https://api.nokotime.com/v2/entries/31803930/invoiced_outside_of_freckle",
        "invoiced_outside_of_noko_url": "https://api.nokotime.com/v2/entries/31803930/marked_as_invoiced",
        "approved_url": "https://api.nokotime.com/v2/entries/31803930/approved",
        "unapproved_url": "https://api.nokotime.com/v2/entries/31803930/unapproved"
    },
    {
        "id": 31803926,
        "date": "2022-07-14",
        "billable": false,
        "minutes": 360,
        "description": "",
        "created_at": "2022-07-18T07:56:35Z",
        "updated_at": "2022-07-18T07:56:35Z",
        "approved_at": null,
        "source_url": null,
        "user": {
            "id": 78165,
            "email": "some.person@armakuni.com",
            "first_name": "Some",
            "last_name": "Person",
            "profile_image_url": "https://cdn.nokotime.com/images/user_icons/default-ig-72x722x.png",
            "url": "https://api.nokotime.com/v2/users/12345"
        },
        "approved_by": null,
        "tags": [],
        "project": {
            "id": 654893,
            "name": "Some project",
            "billing_increment": 5,
            "enabled": true,
            "billable": false,
            "color": "#5b7a11",
            "url": "https://api.nokotime.com/v2/projects/123456"
        },
        "url": "https://api.nokotime.com/v2/entries/31803926",
        "invoiced_outside_of_freckle_url": "https://api.nokotime.com/v2/entries/31803926/invoiced_outside_of_freckle",
        "invoiced_outside_of_noko_url": "https://api.nokotime.com/v2/entries/31803926/marked_as_invoiced",
        "approved_url": "https://api.nokotime.com/v2/entries/31803926/approved",
        "unapproved_url": "https://api.nokotime.com/v2/entries/31803926/unapproved"
    },
    {
        "id": 31803924,
        "date": "2022-07-14",
        "billable": true,
        "minutes": 120,
        "description": "",
        "created_at": "2022-07-18T07:56:22Z",
        "updated_at": "2022-07-18T07:56:22Z",
        "approved_at": null,
        "source_url": null,
        "user": {
            "id": 78165,
            "email": "some.person@armakuni.com",
            "first_name": "Some",
            "last_name": "Person",
            "profile_image_url": "https://cdn.nokotime.com/images/user_icons/default-ig-72x722x.png",
            "url": "https://api.nokotime.com/v2/users/12345"
        },
        "approved_by": null,
        "tags": [],
        "project": {
            "id": 654894,
            "name": "Some project",
            "billing_increment": 60,
            "enabled": true,
            "billable": true,
            "color": "#0f6953",
            "url": "https://api.nokotime.com/v2/projects/123456"
        },
        "url": "https://api.nokotime.com/v2/entries/31803924",
        "invoiced_outside_of_freckle_url": "https://api.nokotime.com/v2/entries/31803924/invoiced_outside_of_freckle",
        "invoiced_outside_of_noko_url": "https://api.nokotime.com/v2/entries/31803924/marked_as_invoiced",
        "approved_url": "https://api.nokotime.com/v2/entries/31803924/approved",
        "unapproved_url": "https://api.nokotime.com/v2/entries/31803924/unapproved"
    },
    {
        "id": 31803912,
        "date": "2022-07-13",
        "billable": true,
        "minutes": 240,
        "description": "",
        "created_at": "2022-07-18T07:54:55Z",
        "updated_at": "2022-07-18T07:54:55Z",
        "approved_at": null,
        "source_url": null,
        "user": {
            "id": 78165,
            "email": "some.person@armakuni.com",
            "first_name": "Some",
            "last_name": "Person",
            "profile_image_url": "https://cdn.nokotime.com/images/user_icons/default-ig-72x722x.png",
            "url": "https://api.nokotime.com/v2/users/12345"
        },
        "approved_by": null,
        "tags": [],
        "project": {
            "id": 654894,
            "name": "Some project",
            "billing_increment": 60,
            "enabled": true,
            "billable": true,
            "color": "#0f6953",
            "url": "https://api.nokotime.com/v2/projects/123456"
        },
        "url": "https://api.nokotime.com/v2/entries/31803912",
        "invoiced_outside_of_freckle_url": "https://api.nokotime.com/v2/entries/31803912/invoiced_outside_of_freckle",
        "invoiced_outside_of_noko_url": "https://api.nokotime.com/v2/entries/31803912/marked_as_invoiced",
        "approved_url": "https://api.nokotime.com/v2/entries/31803912/approved",
        "unapproved_url": "https://api.nokotime.com/v2/entries/31803912/unapproved"
    },
    {
        "id": 31803907,
        "date": "2022-07-13",
        "billable": false,
        "minutes": 240,
        "description": "",
        "created_at": "2022-07-18T07:54:26Z",
        "updated_at": "2022-07-18T07:54:26Z",
        "approved_at": null,
        "source_url": null,
        "user": {
            "id": 78165,
            "email": "some.person@armakuni.com",
            "first_name": "Some",
            "last_name": "Person",
            "profile_image_url": "https://cdn.nokotime.com/images/user_icons/default-ig-72x722x.png",
            "url": "https://api.nokotime.com/v2/users/12345"
        },
        "approved_by": null,
        "tags": [],
        "project": {
            "id": 609863,
            "name": "Some project",
            "billing_increment": 5,
            "enabled": true,
            "billable": false,
            "color": "#ef5555",
            "url": "https://api.nokotime.com/v2/projects/123456"
        },
        "url": "https://api.nokotime.com/v2/entries/31803907",
        "invoiced_outside_of_freckle_url": "https://api.nokotime.com/v2/entries/31803907/invoiced_outside_of_freckle",
        "invoiced_outside_of_noko_url": "https://api.nokotime.com/v2/entries/31803907/marked_as_invoiced",
        "approved_url": "https://api.nokotime.com/v2/entries/31803907/approved",
        "unapproved_url": "https://api.nokotime.com/v2/entries/31803907/unapproved"
    },
    {
        "id": 31803902,
        "date": "2022-07-12",
        "billable": false,
        "minutes": 480,
        "description": "",
        "created_at": "2022-07-18T07:53:53Z",
        "updated_at": "2022-07-18T07:53:53Z",
        "approved_at": null,
        "source_url": null,
        "user": {
            "id": 78165,
            "email": "some.person@armakuni.com",
            "first_name": "Some",
            "last_name": "Person",
            "profile_image_url": "https://cdn.nokotime.com/images/user_icons/default-ig-72x722x.png",
            "url": "https://api.nokotime.com/v2/users/12345"
        },
        "approved_by": null,
        "tags": [],
        "project": {
            "id": 654893,
            "name": "Some project",
            "billing_increment": 5,
            "enabled": true,
            "billable": false,
            "color": "#5b7a11",
            "url": "https://api.nokotime.com/v2/projects/123456"
        },
        "url": "https://api.nokotime.com/v2/entries/31803902",
        "invoiced_outside_of_freckle_url": "https://api.nokotime.com/v2/entries/31803902/invoiced_outside_of_freckle",
        "invoiced_outside_of_noko_url": "https://api.nokotime.com/v2/entries/31803902/marked_as_invoiced",
        "approved_url": "https://api.nokotime.com/v2/entries/31803902/approved",
        "unapproved_url": "https://api.nokotime.com/v2/entries/31803902/unapproved"
    },
    {
        "id": 31803900,
        "date": "2022-07-11",
        "billable": true,
        "minutes": 240,
        "description": "",
        "created_at": "2022-07-18T07:53:38Z",
        "updated_at": "2022-07-18T07:53:38Z",
        "approved_at": null,
        "source_url": null,
        "user": {
            "id": 78165,
            "email": "some.person@armakuni.com",
            "first_name": "Some",
            "last_name": "Person",
            "profile_image_url": "https://cdn.nokotime.com/images/user_icons/default-ig-72x722x.png",
            "url": "https://api.nokotime.com/v2/users/12345"
        },
        "approved_by": null,
        "tags": [],
        "project": {
            "id": 654894,
            "name": "Some project",
            "billing_increment": 60,
            "enabled": true,
            "billable": true,
            "color": "#0f6953",
            "url": "https://api.nokotime.com/v2/projects/123456"
        },
        "url": "https://api.nokotime.com/v2/entries/31803900",
        "invoiced_outside_of_freckle_url": "https://api.nokotime.com/v2/entries/31803900/invoiced_outside_of_freckle",
        "invoiced_outside_of_noko_url": "https://api.nokotime.com/v2/entries/31803900/marked_as_invoiced",
        "approved_url": "https://api.nokotime.com/v2/entries/31803900/approved",
        "unapproved_url": "https://api.nokotime.com/v2/entries/31803900/unapproved"
    },
    {
        "id": 31803895,
        "date": "2022-07-11",
        "billable": false,
        "minutes": 240,
        "description": "",
        "created_at": "2022-07-18T07:53:24Z",
        "updated_at": "2022-07-18T07:53:24Z",
        "approved_at": null,
        "source_url": null,
        "user": {
            "id": 78165,
            "email": "some.person@armakuni.com",
            "first_name": "Some",
            "last_name": "Person",
            "profile_image_url": "https://cdn.nokotime.com/images/user_icons/default-ig-72x722x.png",
            "url": "https://api.nokotime.com/v2/users/12345"
        },
        "approved_by": null,
        "tags": [],
        "project": {
            "id": 609863,
            "name": "Some project",
            "billing_increment": 5,
            "enabled": true,
            "billable": false,
            "color": "#ef5555",
            "url": "https://api.nokotime.com/v2/projects/123456"
        },
        "url": "https://api.nokotime.com/v2/entries/31803895",
        "invoiced_outside_of_freckle_url": "https://api.nokotime.com/v2/entries/31803895/invoiced_outside_of_freckle",
        "invoiced_outside_of_noko_url": "https://api.nokotime.com/v2/entries/31803895/marked_as_invoiced",
        "approved_url": "https://api.nokotime.com/v2/entries/31803895/approved",
        "unapproved_url": "https://api.nokotime.com/v2/entries/31803895/unapproved"
    },
    {
        "id": 31753178,
        "date": "2022-07-08",
        "billable": false,
        "minutes": 480,
        "description": "",
        "created_at": "2022-07-08T20:47:19Z",
        "updated_at": "2022-07-08T20:47:19Z",
        "approved_at": null,
        "source_url": null,
        "user": {
            "id": 78165,
            "email": "some.person@armakuni.com",
            "first_name": "Some",
            "last_name": "Person",
            "profile_image_url": "https://cdn.nokotime.com/images/user_icons/default-ig-72x722x.png",
            "url": "https://api.nokotime.com/v2/users/12345"
        },
        "approved_by": null,
        "tags": [],
        "project": {
            "id": 620570,
            "name": "Some project",
            "billing_increment": 5,
            "enabled": true,
            "billable": false,
            "color": "#0f6953",
            "url": "https://api.nokotime.com/v2/projects/123456"
        },
        "url": "https://api.nokotime.com/v2/entries/31753178",
        "invoiced_outside_of_freckle_url": "https://api.nokotime.com/v2/entries/31753178/invoiced_outside_of_freckle",
        "invoiced_outside_of_noko_url": "https://api.nokotime.com/v2/entries/31753178/marked_as_invoiced",
        "approved_url": "https://api.nokotime.com/v2/entries/31753178/approved",
        "unapproved_url": "https://api.nokotime.com/v2/entries/31753178/unapproved"
    }
]
